pygments_molokai/__init__.py
pygments_molokai/molokai.py
pygments_molokai-0.0.3.dist-info/entry_points.txt
pygments_molokai-0.0.3.dist-info/LICENSE
pygments_molokai-0.0.3.dist-info/WHEEL
pygments_molokai-0.0.3.dist-info/METADATA
pygments_molokai-0.0.3.dist-info/RECORD
