Metadata-Version: 2.1
Name: pygments-molokai
Version: 0.0.3
Summary: A Pygments style providing the Molokai colour scheme.
Home-page: https://github.com/gbpoole/pygments-molokai
License: MIT
Keywords: syntax,highlighting,pygments,style
Author: Gregory Poole
Author-email: gbpoole@gmail.com
Requires-Python: >=3.9,<4.0
Classifier: License :: OSI Approved :: MIT License
Classifier: Programming Language :: Python :: 3
Classifier: Programming Language :: Python :: 3.10
Classifier: Programming Language :: Python :: 3.9
Project-URL: Repository, https://github.com/gbpoole/pygments-molokai
